RsInstrument/RsInstrument.py
RsInstrument/__init__.py
RsInstrument/mcp.py
RsInstrument/py.typed
RsInstrument/Fixed_Files/Events.py
RsInstrument/Fixed_Files/Reliability.py
RsInstrument/Fixed_Files/Utilities.py
RsInstrument/Fixed_Files/__init__.py
RsInstrument/Internal/ArgLinkedEventArgs.py
RsInstrument/Internal/ArgSingle.py
RsInstrument/Internal/ArgSingleList.py
RsInstrument/Internal/ArgSingleSuppressed.py
RsInstrument/Internal/ArgStringComposer.py
RsInstrument/Internal/ArgStruct.py
RsInstrument/Internal/ArgStructList.py
RsInstrument/Internal/ArgStructStringParser.py
RsInstrument/Internal/CommandsGroup.py
RsInstrument/Internal/ContextManagers.py
RsInstrument/Internal/Conversions.py
RsInstrument/Internal/ConverterFromScpiString.py
RsInstrument/Internal/ConverterToScpiString.py
RsInstrument/Internal/Core.py
RsInstrument/Internal/GlobalData.py
RsInstrument/Internal/Instrument.py
RsInstrument/Internal/InstrumentErrors.py
RsInstrument/Internal/InstrumentOptions.py
RsInstrument/Internal/InstrumentSettings.py
RsInstrument/Internal/InternalLinker.py
RsInstrument/Internal/IoTransferEventArgs.py
RsInstrument/Internal/Properties.py
RsInstrument/Internal/RepeatedCapability.py
RsInstrument/Internal/ScpiEnums.py
RsInstrument/Internal/ScpiLogger.py
RsInstrument/Internal/StreamReader.py
RsInstrument/Internal/StreamWriter.py
RsInstrument/Internal/StructBase.py
RsInstrument/Internal/Types.py
RsInstrument/Internal/Utilities.py
RsInstrument/Internal/VisaPluginSocketIo.py
RsInstrument/Internal/VisaSession.py
RsInstrument/Internal/VisaSessionSim.py
RsInstrument/Internal/__init__.py
rsinstrument-1.122.0.dist-info/licenses/LICENSE
rsinstrument-1.122.0.dist-info/METADATA
rsinstrument-1.122.0.dist-info/WHEEL
rsinstrument-1.122.0.dist-info/entry_points.txt
rsinstrument-1.122.0.dist-info/top_level.txt
rsinstrument-1.122.0.dist-info/RECORD
