Metadata-Version: 2.4
Name: RsInstrument
Version: 1.122.0
Summary: VISA or Socket Communication Module for Rohde & Schwarz Instruments
Author: Rohde & Schwarz GmbH & Co. KG
Maintainer: Rohde & Schwarz GmbH & Co. KG
License-Expression: MIT
Project-URL: Documentation, https://rsinstrument.readthedocs.io/
Project-URL: Examples, https://github.com/Rohde-Schwarz/Examples/
Project-URL: Repository, https://github.com/Rohde-Schwarz/RsInstrument
Keywords: RsInstrument,VISA,RohdeSchwarz
Classifier: Development Status :: 5 - Production/Stable
Classifier: Intended Audience :: Developers
Classifier: Topic :: Scientific/Engineering :: Instrument Drivers
Classifier: Programming Language :: Python :: 3
Classifier: Programming Language :: Python :: 3.10
Classifier: Programming Language :: Python :: 3.11
Classifier: Programming Language :: Python :: 3.12
Classifier: Programming Language :: Python :: 3.13
Requires-Python: >=3.10
License-File: LICENSE
Requires-Dist: pyvisa>=1.13.0
Requires-Dist: typing-extensions>=4.0.0
Provides-Extra: mcp
Requires-Dist: mcp; extra == "mcp"
Dynamic: license-file
